MANIFEST.in
README.md
VERSION
setup.py
marian_client/__init__.py
marian_client/quote_manager.py
marian_client/version.py
marian_client.egg-info/PKG-INFO
marian_client.egg-info/SOURCES.txt
marian_client.egg-info/dependency_links.txt
marian_client.egg-info/requires.txt
marian_client.egg-info/top_level.txt