Metadata-Version: 2.1
Name: marian-client
Version: 0.16.0
Summary: UNKNOWN
Home-page: https://github.com/Qordobacode/client.marian
Author: Qordoba
Author-email: Melisa Stal <melisa@qordoba.com>, Sam Havens <sam.havens@qordoba.com>
License: MIT
Platform: UNKNOWN
Classifier: Development Status :: 3 - Alpha
Classifier: Intended Audience :: Science/Research
Classifier: Intended Audience :: Developers
Classifier: Intended Audience :: Information Technology
Classifier: License :: OSI Approved :: MIT License
Classifier: Operating System :: OS Independent
Classifier: Natural Language :: English
Classifier: Programming Language :: Python :: 3.6
Classifier: Programming Language :: Python :: 3.7
Classifier: Topic :: Scientific/Engineering :: Artificial Intelligence
Classifier: Topic :: Text Processing :: Linguistic
Requires-Python: >=3.6.4
